[
  {
    "code": "012450",
    "name": "한화에어로스페이스",
    "smart_money_score": 90,
    "signal": "매수",
    "foreign_net": 40738
  },
  {
    "code": "000720",
    "name": "현대건설",
    "smart_money_score": 90,
    "signal": "매수",
    "foreign_net": 310561
  },
  {
    "code": "047040",
    "name": "대우건설",
    "smart_money_score": 89,
    "signal": "매수",
    "foreign_net": 3703306
  },
  {
    "code": "475150",
    "name": "SK이터닉스",
    "smart_money_score": 89,
    "signal": "매수",
    "foreign_net": 63197
  },
  {
    "code": "476060",
    "name": "온코닉테라퓨틱스",
    "smart_money_score": 89,
    "signal": "매수",
    "foreign_net": 127070
  },
  {
    "code": "034020",
    "name": "두산에너빌리티",
    "smart_money_score": 88,
    "signal": "매수",
    "foreign_net": 829800
  },
  {
    "code": "347850",
    "name": "디앤디파마텍",
    "smart_money_score": 88,
    "signal": "매수",
    "foreign_net": 455527
  },
  {
    "code": "263750",
    "name": "펄어비스",
    "smart_money_score": 88,
    "signal": "매수",
    "foreign_net": 65929
  },
  {
    "code": "452280",
    "name": "한선엔지니어링",
    "smart_money_score": 87,
    "signal": "매수",
    "foreign_net": 271453
  },
  {
    "code": "230240",
    "name": "에치에프알",
    "smart_money_score": 80,
    "signal": "매수",
    "foreign_net": 0
  },
  {
    "code": "005935",
    "name": "삼성전자우",
    "smart_money_score": 79,
    "signal": "매수",
    "foreign_net": -397711
  },
  {
    "code": "010140",
    "name": "삼성중공업",
    "smart_money_score": 79,
    "signal": "매수",
    "foreign_net": -70071
  },
  {
    "code": "267260",
    "name": "HD현대일렉트릭",
    "smart_money_score": 79,
    "signal": "매수",
    "foreign_net": 0
  },
  {
    "code": "047810",
    "name": "한국항공우주",
    "smart_money_score": 79,
    "signal": "매수",
    "foreign_net": 0
  },
  {
    "code": "010120",
    "name": "LS ELECTRIC",
    "smart_money_score": 79,
    "signal": "매수",
    "foreign_net": 0
  },
  {
    "code": "005380",
    "name": "현대차",
    "smart_money_score": 78,
    "signal": "매수",
    "foreign_net": -200951
  },
  {
    "code": "000270",
    "name": "기아",
    "smart_money_score": 78,
    "signal": "매수",
    "foreign_net": -410163
  },
  {
    "code": "009150",
    "name": "삼성전기",
    "smart_money_score": 78,
    "signal": "매수",
    "foreign_net": 0
  },
  {
    "code": "278470",
    "name": "에이피알",
    "smart_money_score": 78,
    "signal": "매수",
    "foreign_net": 0
  },
  {
    "code": "456160",
    "name": "지투지바이오",
    "smart_money_score": 78,
    "signal": "매수",
    "foreign_net": -106436
  }
]